index.py
fis_mcp_server-2.2.0.dist-info/licenses/LICENSE
validate/validator.py
fis_mcp_server-2.2.0.dist-info/METADATA
fis_mcp_server-2.2.0.dist-info/WHEEL
fis_mcp_server-2.2.0.dist-info/entry_points.txt
fis_mcp_server-2.2.0.dist-info/top_level.txt
fis_mcp_server-2.2.0.dist-info/RECORD
